canary_cli/__init__.py
canary_cli/main.py
canary_cli-0.1.dev3.dist-info/METADATA
canary_cli-0.1.dev3.dist-info/WHEEL
canary_cli-0.1.dev3.dist-info/entry_points.txt
canary_cli-0.1.dev3.dist-info/licenses/LICENSE
canary_cli-0.1.dev3.dist-info/RECORD
