Metadata-Version: 2.4
Name: canary-cli
Version: 0.1.dev3
Summary: command line interface for canary-cd
Project-URL: documentation, https://docs.rehborn.dev
Project-URL: source, https://github.com/rehborn/canary-cli.git
Author-email: Dominique Rehborn <dominique@rehborn.dev>
License-Expression: Apache-2.0
License-File: LICENSE
Classifier: Programming Language :: Python :: 3
Classifier: Programming Language :: Python :: 3.12
Classifier: Programming Language :: Python :: 3.13
Classifier: Programming Language :: Python :: 3.14
Classifier: Programming Language :: Python :: 3.15
Requires-Python: <4,>=3.12
Requires-Dist: humanize<5.0.0,>=4.11.0
Requires-Dist: python-dotenv<2.0.0,>=1.0.1
Requires-Dist: pyyaml<7.0.0,>=6.0.2
Requires-Dist: questionary<3.0.0,>=2.1.0
Requires-Dist: requests<3.0.0,>=2.32.3
Requires-Dist: typer<0.18.0,>=0.17.3
